ha/__about__.py
ha/__init__.py
ha/attention.py
ha/attention_loop.py
ha/beam.py
ha/checkpoint.py
ha/ctc.py
ha/data.py
ha/init.py
ha/loop.py
ha/lora.py
ha/mlm.py
ha/model.py
ha/optim.py
ha/resnet.py
ha/rnnlm.py
ha/scan.py
ha/star.py
ha/symbol_tape.py
ha/transducer.py
ha/xen.py
haloop-0.0.10.dist-info/METADATA
haloop-0.0.10.dist-info/WHEEL
haloop-0.0.10.dist-info/entry_points.txt
haloop-0.0.10.dist-info/licenses/LICENSE
haloop-0.0.10.dist-info/RECORD
