Metadata-Version: 2.1
Name: haloop
Version: 0.0.10
Summary: speech agent for 100 hours
Project-URL: Documentation, https://github.com/proger/haloop#readme
Project-URL: Issues, https://github.com/proger/haloop/issues
Project-URL: Source, https://github.com/proger/haloop
Author-email: Volodymyr Kyrylov <vol@wilab.org.ua>
License-Expression: GPL-3.0-or-later
License-File: LICENSE
Classifier: Development Status :: 4 - Beta
Classifier: Programming Language :: Python
Classifier: Programming Language :: Python :: 3.10
Classifier: Programming Language :: Python :: 3.11
Classifier: Programming Language :: Python :: Implementation :: CPython
Requires-Python: >=3.10
Requires-Dist: click
Requires-Dist: g2p-en
Requires-Dist: kaldialign
Requires-Dist: rich
Requires-Dist: torch
Requires-Dist: torchaudio
Requires-Dist: wandb
